nlpio/__init__.py
nlpio/contractions.py
nlpio/nlpio.py
nlpio-0.2.dist-info/METADATA
nlpio-0.2.dist-info/WHEEL
nlpio-0.2.dist-info/top_level.txt
nlpio-0.2.dist-info/RECORD
